README.rst
setup.py
PyDataProc/Chain.py
PyDataProc/DataRow.py
PyDataProc/DataSource.py
PyDataProc/DataTable.py
PyDataProc/FileUtil.py
PyDataProc/LinkedMap.py
PyDataProc/Parameter.py
PyDataProc/PyDataHub.py
PyDataProc/PyEmail.py
PyDataProc/__init__.py
PyDataProc/config.py
PyDataProc.egg-info/PKG-INFO
PyDataProc.egg-info/SOURCES.txt
PyDataProc.egg-info/dependency_links.txt
PyDataProc.egg-info/top_level.txt
PyDataProc.egg-info/zip-safe